README.md
setup.py
src/poppy/__init__.py
src/poppy/hello.py
src/poppylib.egg-info/PKG-INFO
src/poppylib.egg-info/SOURCES.txt
src/poppylib.egg-info/dependency_links.txt
src/poppylib.egg-info/top_level.txt